logstash/__init__.py
logstash/formatter.py
logstash/handler_amqp.py
logstash/handler_http.py
logstash/handler_tcp.py
logstash/handler_udp.py
python3_http_logstash-0.4.74.dist-info/LICENSE
python3_http_logstash-0.4.74.dist-info/METADATA
python3_http_logstash-0.4.74.dist-info/WHEEL
python3_http_logstash-0.4.74.dist-info/top_level.txt
python3_http_logstash-0.4.74.dist-info/RECORD
